excel_mcp/__main__.py
excel_mcp/calculations.py
excel_mcp/cell_utils.py
excel_mcp/cell_validation.py
excel_mcp/chart.py
excel_mcp/data.py
excel_mcp/data_range_analyzer.bak
excel_mcp/data_range_analyzer.py
excel_mcp/exceptions.py
excel_mcp/formatting.py
excel_mcp/pivot.bak
excel_mcp/pivot.py
excel_mcp/server.py
excel_mcp/sheet.py
excel_mcp/tables.py
excel_mcp/validation.py
excel_mcp/workbook.py
knp_mcp_excel-0.0.7.dist-info/METADATA
knp_mcp_excel-0.0.7.dist-info/WHEEL
knp_mcp_excel-0.0.7.dist-info/entry_points.txt
knp_mcp_excel-0.0.7.dist-info/licenses/LICENSE
knp_mcp_excel-0.0.7.dist-info/RECORD
